verify_access_autoconf/__init__.py
verify_access_autoconf/__main__.py
verify_access_autoconf/access_control.py
verify_access_autoconf/appliance.py
verify_access_autoconf/configure.py
verify_access_autoconf/container.py
verify_access_autoconf/federation.py
verify_access_autoconf/webseal.py
verify_access_autoconf/util/__init__.py
verify_access_autoconf/util/configure_util.py
verify_access_autoconf/util/constants.py
verify_access_autoconf/util/data_util.py
verify_access_autoconf-0.3.5.dist-info/LICENCE.md
verify_access_autoconf-0.3.5.dist-info/METADATA
verify_access_autoconf-0.3.5.dist-info/WHEEL
verify_access_autoconf-0.3.5.dist-info/top_level.txt
verify_access_autoconf-0.3.5.dist-info/RECORD
