Metadata-Version: 2.1
Name: verify-access-autoconf
Version: 0.3.5
Summary: YAML based configuration automation for IBM Security Verify Access
Author: Lachlan Gleeson
Author-email: lgleeson@au1.ibm.com
License: Apache2.0
Project-URL: Homepage, https://github.com/lachlan-ibm/verify_access_autoconf
Project-URL: Documentation, https://lachlan-ibm.github.io/verify_access_autoconf
Project-URL: Source, https://github.com/lachlan-ibm/verify_access_autoconf
Project-URL: Tracker, https://github.com/lachlan-ibm/verify_access_autoconf/issues
Keywords: isva,isam,ibm security access manager,ibm security verify access
License-File: LICENCE.md
Requires-Dist: requests
Requires-Dist: PyYAML
Requires-Dist: pyisva
Requires-Dist: kubernetes
Requires-Dist: docker-compose
Requires-Dist: typing
